ordered_set/__init__.py
ordered_set/py.typed
ordered_set/test/__init__.py
ordered_set/test/_test_mypy.py
ordered_set/test/_test_ordered_set_all.py
ordered_set/test/pytest_util.py
ordered_set/test/test_ordered_set_1.py
ordered_set/test/test_ordered_set_2.py
ordered_set/test/test_ordered_set_3.py
stableset-5.2.2.dist-info/METADATA
stableset-5.2.2.dist-info/WHEEL
stableset-5.2.2.dist-info/top_level.txt
stableset-5.2.2.dist-info/RECORD
