Metadata-Version: 2.4
Name: stableset
Version: 5.2.2
Summary: StableSet and OrderedSet are sets that remembers their order, and allows looking up its items by their index in that order.
Home-page: https://github.com/idanmiara/ordered-set
Author: Elia Robyn Lake, Idan Miara
Author-email: Elia Robyn Lake <gh@arborelia.net>, Idan Miara <idan@miara.com>
License: Copyright (c) 2012-2022 Elia Robyn Lake, 2023 Idan Miara
Project-URL: Home, https://github.com/rspeer/ordered-set
Classifier: Development Status :: 5 - Production/Stable
Classifier: Intended Audience :: Developers
Classifier: License :: OSI Approved :: MIT License
Classifier: Programming Language :: Python
Classifier: Programming Language :: Python :: 3
Classifier: Programming Language :: Python :: 3.8
Classifier: Programming Language :: Python :: 3.9
Classifier: Programming Language :: Python :: 3.10
Classifier: Programming Language :: Python :: Implementation :: CPython
Classifier: Programming Language :: Python :: Implementation :: PyPy
Requires-Python: >=3.8
Provides-Extra: dev
Requires-Dist: pytest; extra == "dev"
Requires-Dist: black; extra == "dev"
Requires-Dist: mypy; extra == "dev"
Dynamic: author
Dynamic: home-page
Dynamic: requires-python
Dynamic: summary
